{
  "generated_at_utc": "2026-07-08T09:22:44.843992Z",
  "prices": {
    "CASH": 100.0,
    "MSE.PA": 6029.5831,
    "ARKA.L": 312.8,
    "EMRD.L": 7561.2858,
    "LBUL.L": 12787.6008,
    "XS2D.L": 25984.6105,
    "VUAG.L": 10754.0001,
    "LQQ3.L": 30306.3125,
    "MIDD.L": 2120.0,
    "EIMI.L": 3949.3546,
    "SGLN.L": 5896.4995,
    "EMIM.L": 3947.0,
    "GDGB.L": 6234.0,
    "SEMI.L": 1500.8,
    "EUE.L": 5444.8501,
    "IUCM.L": 1044.0633,
    "MOAT.L": 4795.9128,
    "VERX.L": 4218.0,
    "FTAL.L": 9015.0002,
    "RBOT.L": 1497.7855,
    "VWRP.L": 13953.9993
  }
}