{
  "generated_at_utc": "2026-06-22T12:45:32.460632Z",
  "prices": {
    "CASH": 100.0,
    "MSE.PA": 6193.8112,
    "ARKA.L": 313.2,
    "EMRD.L": 8370.8295,
    "LBUL.L": 13791.1484,
    "XS2D.L": 26148.4816,
    "VUAG.L": 10927.9999,
    "LQQ3.L": 36904.0,
    "MIDD.L": 2139.9541,
    "EIMI.L": 4373.8827,
    "SGLN.L": 6158.6997,
    "EMIM.L": 4378.0,
    "GDGB.L": 6948.0003,
    "SEMI.L": 1842.7999,
    "EUE.L": 5601.0,
    "IUCM.L": 1042.4735,
    "MOAT.L": 4637.4847,
    "VERX.L": 4295.9999,
    "FTAL.L": 8980.0003,
    "RBOT.L": 1648.9254,
    "VWRP.L": 14366.0004
  }
}