{
  "generated_at_utc": "2026-07-15T14:43:46Z",
  "data_asof": "2026-07-15",
  "daily_rows": 5849,
  "quote_price": 65.25,
  "quote_timestamp": "2026-07-15",
  "quote_source": "Yahoo Finance chart endpoint",
  "sources": {
    "daily_yahoo": {
      "url": "https://query1.finance.yahoo.com/v8/finance/chart/EEM?period1=0&period2=1784213026&interval=1d&events=history&includeAdjustedClose=true",
      "ok": true,
      "status": 200
    }
  },
  "strategy": {
    "name": "Guarded A5/B25 SMA20 Lead (MSCI EM, max 1x)",
    "parameters": {
      "triggerA": 0.05,
      "triggerB": 0.25,
      "hold2": 0.4,
      "hold3": 0.15,
      "leadPct": 0.0075,
      "maxLeverage": 1.0
    }
  },
  "official_signal": {
    "latest": {
      "date": "2026-07-15",
      "close": 65.25
    },
    "latestSma": 67.4745002746582,
    "highWater": 71.20999908447266,
    "highWaterDate": "2026-06-22",
    "latestDd": -0.08369609831622982,
    "regime": "tier2",
    "entryClose": 67.56999969482422,
    "entryDate": "2026-07-06",
    "recoveryTarget": 94.5979995727539,
    "aboveSma": false,
    "recoveryOk": false,
    "targetLeverage": 0,
    "activeEntryClose": null,
    "activeEntryDate": null,
    "activeEntryLeverage": null,
    "activeEntryPnl": null,
    "explanation": "2x tier is armed, but lead guard failed; using base cash/1x rule."
  },
  "provisional_signal": {
    "latest": {
      "date": "2026-07-15",
      "close": 65.25
    },
    "latestSma": 67.2495002746582,
    "highWater": 71.20999908447266,
    "highWaterDate": "2026-06-22",
    "latestDd": -0.08369609831622982,
    "regime": "tier2",
    "entryClose": 67.56999969482422,
    "entryDate": "2026-07-06",
    "recoveryTarget": 94.5979995727539,
    "aboveSma": false,
    "recoveryOk": false,
    "targetLeverage": 0,
    "activeEntryClose": null,
    "activeEntryDate": null,
    "activeEntryLeverage": null,
    "activeEntryPnl": null,
    "explanation": "2x tier is armed, but lead guard failed; using base cash/1x rule."
  },
  "trade_alert_state": {
    "last_observed_asof": "2026-07-15",
    "last_observed_target_leverage": 0,
    "last_observed_target_label": "cash",
    "last_checked_at_utc": "2026-07-15T14:43:46Z",
    "last_email_sent_on": "2026-07-07",
    "last_transition": {
      "id": "2026-07-06:1->2026-07-07:0",
      "detected_at_utc": "2026-07-07T15:41:33Z",
      "previous_asof": "2026-07-06",
      "current_asof": "2026-07-07",
      "old_target_leverage": 1,
      "new_target_leverage": 0,
      "old_target_label": "1x",
      "new_target_label": "cash",
      "email_sent": true,
      "email_error": null,
      "email_skipped_reason": null
    }
  }
}
