{
  "generated_at_utc": "2026-06-16T06:32:57Z",
  "asset": {
    "ticker": "3BAL.L",
    "name": "WisdomTree EURO STOXX Banks 3x Daily Leveraged",
    "isin": "IE00BLS09N40",
    "currency": "GBX (LSE)",
    "inception": "2014-12-08"
  },
  "default_strategy": "SMA20 1x/cash",
  "guarded_params": {
    "strategy": "Guarded A5/B25 SMA20 Lead (max 1x)",
    "trigger_a": 0.05,
    "trigger_b": 0.25,
    "lead_pct_below_sma20": 0.0075,
    "x_return": 0.4,
    "y_return": 0.15,
    "max_leverage": 1.0
  },
  "leverage_note": "Max 1x on this tab means the portfolio toggles between cash (T-bills) and fully invested in 3BAL (3x daily EURO STOXX Banks ETP). The default SMA20 rule is above SMA20 = 1x in 3BAL, below SMA20 = cash. Guarded A5/B25 recovery tiers still arm at -5% / -25% but exposure stays at 0 or 100% of the 3x product.",
  "assumptions": {
    "initial_capital": 100.0,
    "annual_inflow_usd": 10.0,
    "trading_cost_pct": 0.001,
    "signal_and_pnl": "Rules on 3BAL price; max 1x = cash vs fully in 3x ETP"
  },
  "sample": {
    "start_date": "2014-12-08",
    "end_date": "2026-06-15",
    "trading_days": 2961
  },
  "strategies": [
    {
      "asset": "3BAL.L (3x EURO STOXX Banks ETP)",
      "ticker": "3BAL.L",
      "strategy": "Buy & hold (always in 3BAL)",
      "start_date": "2014-12-08",
      "end_date": "2026-06-15",
      "trading_days": 2961,
      "cagr": 0.21876159641854698,
      "ann_volatility": 0.8594412968769237,
      "sharpe": 0.40212069071248846,
      "max_drawdown": -0.9753928217298906,
      "calmar": 0.22428050683268946,
      "end_$": 975.4155093832052,
      "rebalances": 2,
      "trading_costs_total": 0.19990000000000002,
      "pct_cash": 0.033772374197906116,
      "pct_invested": 99.96622762580209
    },
    {
      "asset": "3BAL.L (3x EURO STOXX Banks ETP)",
      "ticker": "3BAL.L",
      "strategy": "SMA20 1x/cash",
      "start_date": "2014-12-08",
      "end_date": "2026-06-15",
      "trading_days": 2961,
      "cagr": 0.1548357110019256,
      "ann_volatility": 0.5289726826123857,
      "sharpe": 0.3348766553335409,
      "max_drawdown": -0.8776025273737939,
      "calmar": 0.1764303385329439,
      "end_$": 524.4231500071363,
      "rebalances": 378,
      "trading_costs_total": 48.360490654716095,
      "pct_cash": 46.9436001350895,
      "pct_invested": 53.0563998649105,
      "pct_days_cash": 46.909827760891595
    },
    {
      "asset": "3BAL.L (3x EURO STOXX Banks ETP)",
      "ticker": "3BAL.L",
      "strategy": "Guarded A5/B25 SMA20 Lead (max 1x)",
      "start_date": "2014-12-08",
      "end_date": "2026-06-15",
      "trading_days": 2961,
      "cagr": 0.15770887484742935,
      "ann_volatility": 0.5431031236588661,
      "sharpe": 0.27549493179573414,
      "max_drawdown": -0.8968276189102314,
      "calmar": 0.1758519380113062,
      "end_$": 539.6494507946932,
      "rebalances": 382,
      "trading_costs_total": 40.60457111924189,
      "pct_cash": 43.397500844309356,
      "pct_invested": 56.602499155690644,
      "pct_days_cash": 43.363728470111454,
      "pct_days_1x": 56.636271529888546,
      "tier2_entries": 3,
      "tier3_entries": 2,
      "lead_only_days": 105,
      "guard_blocked_days": 1283
    }
  ],
  "site_strategies": [
    {
      "strategy": "Buy & hold (always in 3BAL)",
      "cagr": 0.21876159641854698,
      "ann_volatility": 0.8594412968769237,
      "sharpe": 0.40212069071248846,
      "max_drawdown": -0.9753928217298906,
      "end_$": 975.4155093832052,
      "rebalances": 2,
      "pct_days_cash": 0.0
    },
    {
      "strategy": "SMA20 1x/cash",
      "cagr": 0.1548357110019256,
      "ann_volatility": 0.5289726826123857,
      "sharpe": 0.3348766553335409,
      "max_drawdown": -0.8776025273737939,
      "end_$": 524.4231500071363,
      "rebalances": 378,
      "pct_days_cash": 46.909827760891595
    },
    {
      "strategy": "Guarded A5/B25 SMA20 Lead (max 1x)",
      "cagr": 0.15770887484742935,
      "ann_volatility": 0.5431031236588661,
      "sharpe": 0.27549493179573414,
      "max_drawdown": -0.8968276189102314,
      "calmar": 0.1758519380113062,
      "end_$": 539.6494507946932,
      "rebalances": 382,
      "trading_costs_total": 40.60457111924189,
      "funding_costs_total": 0.0,
      "pct_days_cash": 43.363728470111454,
      "pct_days_1x": 56.636271529888546,
      "pct_days_2x": 0.0,
      "pct_days_3x": 0.0,
      "tier2_entries": 3,
      "tier3_entries": 2,
      "lead_only_days": 105,
      "guard_blocked_days": 1283,
      "pct_cash": 43.397500844309356
    }
  ],
  "monte_carlo": {
    "strategy": "SMA20 1x/cash",
    "median_cagr": 0.12311003577164159,
    "p10_cagr": -0.04814574648890192,
    "p90_cagr": 0.38612552727588634,
    "median_max_drawdown": -0.792351828834626,
    "p10_max_drawdown": -0.9129799408945043,
    "p90_max_drawdown": -0.6195982051556674,
    "median_sharpe": 0.43469179394978086,
    "median_end_$": 306.3742770346216,
    "prob_max_dd_worse_35pct": 1.0,
    "prob_max_dd_worse_40pct": 1.0,
    "prob_max_dd_worse_50pct": 0.995,
    "prob_end_below_start": 0.165
  },
  "default_vs_buy_hold": {
    "cagr_delta_pp": -6.392588541662136,
    "sharpe_delta": -0.06724403537894758,
    "max_dd_delta_pp": 9.779029435609676,
    "end_value_ratio": 0.5376407745851307
  }
}
